kadena_sdk/__init__.py
kadena_sdk/crypto_lib.py
kadena_sdk/kadena_sdk.py
kadena_sdk/key_pair.py
kadena_sdk/types.py
kadena_sdk/tests/__init__.py
kadena_sdk/tests/crypto_test.py
kadena_sdk/tests/kadena_test.py
kadena_sdk-2.0.5.dist-info/LICENSE
kadena_sdk-2.0.5.dist-info/METADATA
kadena_sdk-2.0.5.dist-info/WHEEL
kadena_sdk-2.0.5.dist-info/top_level.txt
kadena_sdk-2.0.5.dist-info/RECORD
