Metadata-Version: 2.1
Name: kadena-sdk
Version: 2.0.5
Summary: An SDK for interacting with the Kadena Blockchain
Author-email: Luzzotica <sterlinglong0@gmail.com>
Project-URL: Homepage, https://github.com/Luzzotica/KadenaPythonSdk
Project-URL: Bug Tracker, https://github.com/Luzzotica/KadenaPythonSdk/issues
Classifier: Programming Language :: Python :: 3.9
Classifier: License :: OSI Approved :: MIT License
Classifier: Operating System :: OS Independent
Requires-Python: >=3.9
License-File: LICENSE
Requires-Dist: requests (==2.28.1)
Requires-Dist: pynacl (==1.5.0)
Requires-Dist: cffi (==1.15.1)
